[
    {   "image" : "/women-image/w-1.png",
         "title" : "Women Printed Pure Cotton Straight Kurta  (Red).",
         "price" : "Price : ₹359"
        
    },
    {
        "image" : "/women-image/w-2.png",
         "title" : "Women Printed Pure Cotton Flared Kurta  (Maroon, Grey, Beige)",
         "price" : "Price : ₹649"
    },
    {
        "image" : "/women-image/w-3.png",
        "title" : "Women Embroidered Cotton Blend Anarkali Kurta  (Multicolor)",
        "price" : "Price : ₹449"
    },
    {
        "image" : "/women-image/w-12.png",
        "title" : "Women Cotton Blend Kurti Pant Set (Cotton Blend) .",
        "price" : "Price : ₹349"
    },
    {
        "image" : "/women-image/w-5-5.png",
        "title" : "GUTI Women Flared High Rise Blue Jeans High-quality Fabric",
        "price" : "Price : ₹999"
    },
    {
        "image" : "/women-image/w-6-6.png",
        "title" : " KOTTY Women Regular High Rise Blue Jeans Regular High Rise",
        "price" : "Price : ₹599"
    },
    {
        "image" : "/women-image/w-7-7.png",
        "title" : " Puella Women Flared High Rise Blue Jeans Flared High Rise",
        "price" : "Price : ₹529"
    },
    {
        "image" : "/women-image/w-8-8.png",
        "title" : "GUTI  Women Flared High Rise Black Jeans High Rise .",
        "price" : "Price : ₹629"
    },
    {
        "image" : "/women-image/w-9-9.png",
        "title" : "Floral Print,Print Daily Wear Georgette Saree  (Brown) .",
        "price" : "Price : ₹529"
    },
    {
        "image" : "/women-image/w10-10.png",
        "title" : "Printed, Color Block, Blocked Printed, Floral Print, Dyed .",
        "price" : "Price : ₹459"
    },
    {
        "image" : "/women-image/w-11.png",
        "title" : "Self Design Bollywood Net Saree  (Multicolor) Bollywood Net. ",
        "price" : "Price : ₹949"
    },
    {
        "image" : "/women-image/w-4.png",
        "title" : "Digital Print Bollywood Georgette Saree  (Multicolor).",
        "price" : "Price : ₹749"
    },
    {
        "image" : "/women-image/w-13.png",
        "title" : "Women Self Design Round Neck Wool Blend Pink T-Shirt.",
        "price" : "Price : ₹249"
    },
    {
        "image" : "/women-image/w-14.png",
        "title" : "Women Printed Round Neck Wool Blend Maroon T-Shirt.",
        "price" : "Price : ₹349"
    },
    {
        "image" : "/women-image/w-15.png",
        "title" : "Women Printed, Typography Blend Yellow T-Shirt.",
        "price" : "Price : ₹199"
    },
    {
        "image" : "/women-image/w-16.png",
        "title" : "Pack of 2 Women Printed Round Neck Cotton Blend.",
        "price" : "Price : ₹599"
    }
]